fuson_strategy_client/__init__.py
fuson_strategy_client/client.py
fuson_strategy_client-0.1.1.dist-info/METADATA
fuson_strategy_client-0.1.1.dist-info/WHEEL
fuson_strategy_client-0.1.1.dist-info/top_level.txt
fuson_strategy_client-0.1.1.dist-info/RECORD
